{
  "version": "7",
  "dialect": "postgresql",
  "entries": [
    {
      "idx": 0,
      "version": "7",
      "when": 1732632108615,
      "tag": "0000_reflective_shinko_yamashiro",
      "breakpoints": true
    },
    {
      "idx": 1,
      "version": "7",
      "when": 1732633614368,
      "tag": "0001_foamy_black_crow",
      "breakpoints": true
    },
    {
      "idx": 2,
      "version": "7",
      "when": 1732697022175,
      "tag": "0002_lean_sway",
      "breakpoints": true
    },
    {
      "idx": 3,
      "version": "7",
      "when": 1732697247950,
      "tag": "0003_early_sir_ram",
      "breakpoints": true
    },
    {
      "idx": 4,
      "version": "7",
      "when": 1732697489082,
      "tag": "0004_flawless_shard",
      "breakpoints": true
    }
  ]
}